{"note":"This file is an internal implementation detail to speed up HTML report generation. Its format can change at any time. You might be looking for the JSON report: https://coverage.rtfd.io/cmd.html#cmd-json","format":5,"version":"7.9.1","globals":"8899c4c9a49ee27b041fc3c4e4e1df29","files":{"z_b5f384a25ca9e160___init___py":{"hash":"c4e019332790985c70fe77f96909e891","index":{"url":"z_b5f384a25ca9e160___init___py.html","file":"yield_analysis_sdk\\__init__.py","description":"","nums":{"precision":0,"n_files":1,"n_statements":9,"n_excluded":0,"n_missing":0,"n_branches":0,"n_partial_branches":0,"n_missing_branches":0}}},"z_b5f384a25ca9e160_analysis_py":{"hash":"97f9162a30b5b14327754c9ea0c97d14","index":{"url":"z_b5f384a25ca9e160_analysis_py.html","file":"yield_analysis_sdk\\analysis.py","description":"","nums":{"precision":0,"n_files":1,"n_statements":80,"n_excluded":0,"n_missing":17,"n_branches":0,"n_partial_branches":0,"n_missing_branches":0}}},"z_b5f384a25ca9e160_subgraph_py":{"hash":"2734aeb50003d50f96a5355c6997296b","index":{"url":"z_b5f384a25ca9e160_subgraph_py.html","file":"yield_analysis_sdk\\subgraph.py","description":"","nums":{"precision":0,"n_files":1,"n_statements":47,"n_excluded":0,"n_missing":10,"n_branches":0,"n_partial_branches":0,"n_missing_branches":0}}},"z_b5f384a25ca9e160_type_py":{"hash":"29eb3d2b93d4364ca7640a55fdf3ccd7","index":{"url":"z_b5f384a25ca9e160_type_py.html","file":"yield_analysis_sdk\\type.py","description":"","nums":{"precision":0,"n_files":1,"n_statements":81,"n_excluded":0,"n_missing":0,"n_branches":0,"n_partial_branches":0,"n_missing_branches":0}}},"z_b5f384a25ca9e160_acp_py":{"hash":"5f6a1508ffe78b3e3e25a800886fbc92","index":{"url":"z_b5f384a25ca9e160_acp_py.html","file":"yield_analysis_sdk\\acp.py","description":"","nums":{"precision":0,"n_files":1,"n_statements":27,"n_excluded":0,"n_missing":3,"n_branches":0,"n_partial_branches":0,"n_missing_branches":0}}},"z_b5f384a25ca9e160_validators_py":{"hash":"630ba3a10dcf3081326240284dec2ad4","index":{"url":"z_b5f384a25ca9e160_validators_py.html","file":"yield_analysis_sdk\\validators.py","description":"","nums":{"precision":0,"n_files":1,"n_statements":60,"n_excluded":0,"n_missing":13,"n_branches":0,"n_partial_branches":0,"n_missing_branches":0}}},"z_b5f384a25ca9e160_exceptions_py":{"hash":"9f838c473967fa47dcb9ae060abf1de3","index":{"url":"z_b5f384a25ca9e160_exceptions_py.html","file":"yield_analysis_sdk\\exceptions.py","description":"","nums":{"precision":0,"n_files":1,"n_statements":11,"n_excluded":0,"n_missing":0,"n_branches":0,"n_partial_branches":0,"n_missing_branches":0}}}}}