[
    {
        "equal": false,
        "extracted_texts": [
            "Instructions :"
        ],
        "original_text": "Instructions: Record your start and stop dates of your period (bleeding days) within your menstrual cycle every time it occurs..",
        "source_text_list": [
            "Instructions:"
        ],
        "target_text": "Instructions : Enregistrez vos dates de début et de fin de vos règles (jours de saignement) dans votre cycle menstruel chaque fois qu'elles surviennent."
    }
]